get_cover_mcp/__init__.py
get_cover_mcp-0.1.0.dist-info/WHEEL
get_cover_mcp-0.1.0.dist-info/entry_points.txt
get_cover_mcp-0.1.0.dist-info/METADATA
get_cover_mcp-0.1.0.dist-info/RECORD
